glassflow_clickhouse_etl/__init__.py
glassflow_clickhouse_etl/api_client.py
glassflow_clickhouse_etl/client.py
glassflow_clickhouse_etl/dlq.py
glassflow_clickhouse_etl/errors.py
glassflow_clickhouse_etl/pipeline.py
glassflow_clickhouse_etl/tracking.py
glassflow_clickhouse_etl/models/__init__.py
glassflow_clickhouse_etl/models/base.py
glassflow_clickhouse_etl/models/config.py
glassflow_clickhouse_etl/models/data_types.py
glassflow_clickhouse_etl/models/join.py
glassflow_clickhouse_etl/models/pipeline.py
glassflow_clickhouse_etl/models/sink.py
glassflow_clickhouse_etl/models/source.py
glassflow_clickhouse_etl-1.0.0.dist-info/METADATA
glassflow_clickhouse_etl-1.0.0.dist-info/WHEEL
glassflow_clickhouse_etl-1.0.0.dist-info/licenses/LICENSE.md
glassflow_clickhouse_etl-1.0.0.dist-info/RECORD
