Metadata-Version: 2.4
Name: glassflow-clickhouse-etl
Version: 1.0.0
Summary: GlassFlow Clickhouse ETL Python SDK: Create GlassFlow pipelines between Kafka and ClickHouse
Project-URL: Homepage, https://github.com/glassflow/clickhouse-etl-py-sdk
Project-URL: Documentation, https://glassflow.github.io/clickhouse-etl-py-sdk
Project-URL: Repository, https://github.com/glassflow/clickhouse-etl-py-sdk.git
Project-URL: Issues, https://github.com/glassflow/clickhouse-etl-py-sdk/issues
Author-email: GlassFlow <hello@glassflow.dev>
License: MIT
License-File: LICENSE.md
Keywords: clickhouse,data-engineering,data-pipeline,etl,glassflow,kafka,streaming
Classifier: Development Status :: 4 - Beta
Classifier: Intended Audience :: Developers
Classifier: License :: OSI Approved :: MIT License
Classifier: Programming Language :: Python :: 3
Classifier: Programming Language :: Python :: 3.9
Classifier: Programming Language :: Python :: 3.10
Classifier: Programming Language :: Python :: 3.11
Classifier: Topic :: Software Development :: Libraries :: Python Modules
Requires-Python: >=3.9
Requires-Dist: httpx>=0.26.0
Requires-Dist: mixpanel>=4.10.0
Requires-Dist: pydantic>=2.0.0
Requires-Dist: python-dotenv>=1.0.0
Requires-Dist: pyyaml>=6.0.2
Requires-Dist: requests>=2.31.0
Provides-Extra: build
Requires-Dist: build>=1.0.0; extra == 'build'
Requires-Dist: hatch>=1.0.0; extra == 'build'
Requires-Dist: twine>=4.0.0; extra == 'build'
Provides-Extra: test
Requires-Dist: pytest-cov>=4.0.0; extra == 'test'
Requires-Dist: pytest>=7.0.0; extra == 'test'
Requires-Dist: ruff>=0.1.0; extra == 'test'
